flake8_github_annotations/__about__.py
flake8_github_annotations/__init__.py
flake8_github_annotations/formatter.py
flake8_github_annotations-1.1.2.dist-info/METADATA
flake8_github_annotations-1.1.2.dist-info/WHEEL
flake8_github_annotations-1.1.2.dist-info/entry_points.txt
flake8_github_annotations-1.1.2.dist-info/licenses/LICENSE.txt
flake8_github_annotations-1.1.2.dist-info/RECORD
