Metadata-Version: 2.3
Name: flake8-github-annotations
Version: 1.1.2
Summary: A flake8 formatter that turns output into Github Annotations
Project-URL: Documentation, https://github.com/gustavgransbo/flake8-github-annotations#readme
Project-URL: Issues, https://github.com/gustavgransbo/flake8-github-annotations/issues
Project-URL: Source, https://github.com/gustavgransbo/flake8-github-annotations
Author-email: Gustav Gränsbo <gustav.gransbo@gmail.com>
License-Expression: MIT
License-File: LICENSE.txt
Classifier: Programming Language :: Python
Classifier: Programming Language :: Python :: 3.7
Classifier: Programming Language :: Python :: 3.8
Classifier: Programming Language :: Python :: 3.9
Classifier: Programming Language :: Python :: 3.10
Classifier: Programming Language :: Python :: 3.11
Classifier: Programming Language :: Python :: 3.12
Requires-Python: >=3.7
Requires-Dist: flake8>=4.0.0
